library/__init__.py
library/main.py
gowthu1997-0.1.0.dist-info/METADATA
gowthu1997-0.1.0.dist-info/WHEEL
gowthu1997-0.1.0.dist-info/top_level.txt
gowthu1997-0.1.0.dist-info/RECORD
