Metadata-Version: 2.1
Name: gowthu1997
Version: 0.1.0
Summary: its sample
Home-page: UNKNOWN
Author: Gowtham
Author-email: gowthamhegde787@gmail.com
License: Apache License 2.0
Platform: UNKNOWN
Requires-Dist: numpy
Requires-Dist: pandas
